pytest_logger/__init__.py
pytest_logger/plugin.py
pytest_logger-1.1.0.dist-info/LICENSE
pytest_logger-1.1.0.dist-info/METADATA
pytest_logger-1.1.0.dist-info/WHEEL
pytest_logger-1.1.0.dist-info/entry_points.txt
pytest_logger-1.1.0.dist-info/top_level.txt
pytest_logger-1.1.0.dist-info/RECORD
