Metadata-Version: 2.1
Name: pytest-logger
Version: 1.1.0
Summary: Plugin configuring handlers for loggers from Python logging module.
Home-page: https://github.com/aurzenligl/pytest-logger
Author: Krzysztof Laskowski
Author-email: aurzenligl@gmail.com
Maintainer: Krzysztof Laskowski
Maintainer-email: aurzenligl@gmail.com
License: MIT
Keywords: py.test pytest logging
Platform: UNKNOWN
Classifier: Development Status :: 5 - Production/Stable
Classifier: Framework :: Pytest
Classifier: Intended Audience :: Developers
Classifier: Topic :: Software Development :: Testing
Classifier: Programming Language :: Python
Classifier: Programming Language :: Python :: 3
Classifier: Programming Language :: Python :: 3.7
Classifier: Programming Language :: Python :: 3.8
Classifier: Programming Language :: Python :: 3.9
Classifier: Programming Language :: Python :: 3.10
Classifier: Programming Language :: Python :: 3.11
Classifier: Programming Language :: Python :: 3.12
Classifier: Programming Language :: Python :: Implementation :: CPython
Classifier: Programming Language :: Python :: Implementation :: PyPy
Classifier: Operating System :: OS Independent
Classifier: License :: OSI Approved :: MIT License
License-File: LICENSE
Requires-Dist: pytest (>=3.2)
